goolog/__init__.py
goolog-0.0.1.dist-info/LICENSE
goolog-0.0.1.dist-info/METADATA
goolog-0.0.1.dist-info/WHEEL
goolog-0.0.1.dist-info/top_level.txt
goolog-0.0.1.dist-info/RECORD
