Metadata-Version: 2.1
Name: goolog
Version: 0.0.1
Summary: colorful printer
Home-page: https://github.com/YiXiaoCuoHuaiFenZi/goolog
Author: YiXiaoCuoHuaiFenZi(一小撮坏分子)
Author-email: 249664317@qq.com
License: UNKNOWN
Project-URL: Bug Tracker, https://github.com/YiXiaoCuoHuaiFenZi/goolog/issues
Platform: UNKNOWN
Classifier: Programming Language :: Python :: 3
Classifier: License :: OSI Approved :: MIT License
Classifier: Operating System :: OS Independent
Requires-Python: >=3.6
License-File: LICENSE
Provides-Extra: dev
Requires-Dist: build (==0.5.1) ; extra == 'dev'
Requires-Dist: twine (<4,>=3.4.2) ; extra == 'dev'
Requires-Dist: pip-tools (<6,>=5) ; extra == 'dev'
